code/__init__.py
sebaxu-0.2.dist-info/LICENSE.txt
sebaxu-0.2.dist-info/METADATA
sebaxu-0.2.dist-info/WHEEL
sebaxu-0.2.dist-info/top_level.txt
sebaxu-0.2.dist-info/RECORD
